ohsheet/__init__.py
ohsheet/__main__.py
ohsheet/chatcsv.py
ohsheet/ohsheet.py
OhSheet-0.0.1.dist-info/LICENSE
OhSheet-0.0.1.dist-info/METADATA
OhSheet-0.0.1.dist-info/WHEEL
OhSheet-0.0.1.dist-info/entry_points.txt
OhSheet-0.0.1.dist-info/top_level.txt
OhSheet-0.0.1.dist-info/RECORD
