Metadata-Version: 2.1
Name: OhSheet
Version: 0.0.1
Summary: OhSheet.
Author-email: Emery Berger <emery.berger@gmail.com>
Project-URL: Homepage, https://github.com/plasma-umass/OhSheet
Project-URL: Bug Tracker, https://github.com/plasma-umass/OhSheet
Classifier: Programming Language :: Python :: 3
Classifier: Programming Language :: Python :: 3.8
Classifier: Programming Language :: Python :: 3.9
Classifier: Programming Language :: Python :: 3.10
Classifier: Programming Language :: Python :: 3.11
Classifier: Programming Language :: Python :: 3.12
Classifier: License :: OSI Approved :: MIT License
Classifier: Operating System :: OS Independent
Requires-Python: >=3.7
License-File: LICENSE
Requires-Dist: openai (>=0.27.0)
Requires-Dist: openai-async (>=0.0.3)
Requires-Dist: aiohttp (==3.8.3)
